sprockets.handlers.status-0.1.2-py2.7-nspkg.pth
sprockets/handlers/status/__init__.py
sprockets.handlers.status-0.1.2.dist-info/namespace_packages.txt
sprockets.handlers.status-0.1.2.dist-info/top_level.txt
sprockets.handlers.status-0.1.2.dist-info/METADATA
sprockets.handlers.status-0.1.2.dist-info/DESCRIPTION.rst
sprockets.handlers.status-0.1.2.dist-info/metadata.json
sprockets.handlers.status-0.1.2.dist-info/WHEEL
sprockets.handlers.status-0.1.2.dist-info/RECORD
